{"trial_id": "76f22fa22384b92e068ef8cbbecc78ea", "hyperparameters": {"space": [{"class_name": "Boolean", "config": {"name": "structured_data_block_1/normalize", "default": false, "conditions": []}}, {"class_name": "Boolean", "config": {"name": "structured_data_block_1/dense_block_1/use_batchnorm", "default": false, "conditions": []}}, {"class_name": "Choice", "config": {"name": "structured_data_block_1/dense_block_1/num_layers", "default": 2, "conditions": [], "values": [1, 2, 3], "ordered": true}}, {"class_name": "Choice", "config": {"name": "structured_data_block_1/dense_block_1/units_0", "default": 32, "conditions": [], "values": [16, 32, 64, 128, 256, 512, 1024], "ordered": true}}, {"class_name": "Choice", "config": {"name": "structured_data_block_1/dense_block_1/dropout", "default": 0.0, "conditions": [], "values": [0.0, 0.25, 0.5], "ordered": true}}, {"class_name": "Choice", "config": {"name": "structured_data_block_1/dense_block_1/units_1", "default": 32, "conditions": [], "values": [16, 32, 64, 128, 256, 512, 1024], "ordered": true}}, {"class_name": "Choice", "config": {"name": "classification_head_1/dropout", "default": 0, "conditions": [], "values": [0.0, 0.25, 0.5], "ordered": true}}, {"class_name": "Choice", "config": {"name": "optimizer", "default": "adam", "conditions": [], "values": ["adam", "sgd", "adam_weight_decay"], "ordered": false}}, {"class_name": "Choice", "config": {"name": "learning_rate", "default": 0.001, "conditions": [], "values": [0.1, 0.01, 0.001, 0.0001, 2e-05, 1e-05], "ordered": true}}, {"class_name": "Choice", "config": {"name": "structured_data_block_1/dense_block_1/units_2", "default": 32, "conditions": [], "values": [16, 32, 64, 128, 256, 512, 1024], "ordered": true}}], "values": {"structured_data_block_1/normalize": true, "structured_data_block_1/dense_block_1/use_batchnorm": false, "structured_data_block_1/dense_block_1/num_layers": 2, "structured_data_block_1/dense_block_1/units_0": 32, "structured_data_block_1/dense_block_1/dropout": 0.5, "structured_data_block_1/dense_block_1/units_1": 32, "classification_head_1/dropout": 0.5, "optimizer": "adam", "learning_rate": 0.01, "structured_data_block_1/dense_block_1/units_2": 64}}, "metrics": {"metrics": {"loss": {"direction": "min", "observations": [{"value": [1.186087727546692], "step": 0}, {"value": [1.0218523740768433], "step": 1}, {"value": [0.9107897281646729], "step": 2}, {"value": [0.8243212699890137], "step": 3}, {"value": [0.7700307369232178], "step": 4}, {"value": [0.6674280166625977], "step": 5}, {"value": [0.5975114107131958], "step": 6}, {"value": [0.5764811038970947], "step": 7}, {"value": [0.7000137567520142], "step": 8}, {"value": [0.5355163812637329], "step": 9}]}, "accuracy": {"direction": "max", "observations": [{"value": [0.42465752363204956], "step": 0}, {"value": [0.4931506812572479], "step": 1}, {"value": [0.5890411138534546], "step": 2}, {"value": [0.6164383292198181], "step": 3}, {"value": [0.6712328791618347], "step": 4}, {"value": [0.6712328791618347], "step": 5}, {"value": [0.698630154132843], "step": 6}, {"value": [0.767123281955719], "step": 7}, {"value": [0.6575342416763306], "step": 8}, {"value": [0.8082191944122314], "step": 9}]}, "categorical_accuracy": {"direction": "max", "observations": [{"value": [0.42465752363204956], "step": 0}, {"value": [0.4931506812572479], "step": 1}, {"value": [0.5890411138534546], "step": 2}, {"value": [0.6164383292198181], "step": 3}, {"value": [0.6712328791618347], "step": 4}, {"value": [0.6712328791618347], "step": 5}, {"value": [0.698630154132843], "step": 6}, {"value": [0.767123281955719], "step": 7}, {"value": [0.6575342416763306], "step": 8}, {"value": [0.8082191944122314], "step": 9}]}, "val_loss": {"direction": "min", "observations": [{"value": [0.9278393983840942], "step": 0}, {"value": [0.7817869186401367], "step": 1}, {"value": [0.684821367263794], "step": 2}, {"value": [0.600421667098999], "step": 3}, {"value": [0.540564775466919], "step": 4}, {"value": [0.4981901943683624], "step": 5}, {"value": [0.4680096507072449], "step": 6}, {"value": [0.4409121870994568], "step": 7}, {"value": [0.4197433590888977], "step": 8}, {"value": [0.40033984184265137], "step": 9}]}, "val_accuracy": {"direction": "max", "observations": [{"value": [0.65625], "step": 0}, {"value": [0.71875], "step": 1}, {"value": [0.75], "step": 2}, {"value": [0.75], "step": 3}, {"value": [0.75], "step": 4}, {"value": [0.75], "step": 5}, {"value": [0.78125], "step": 6}, {"value": [0.78125], "step": 7}, {"value": [0.75], "step": 8}, {"value": [0.78125], "step": 9}]}, "val_categorical_accuracy": {"direction": "max", "observations": [{"value": [0.65625], "step": 0}, {"value": [0.71875], "step": 1}, {"value": [0.75], "step": 2}, {"value": [0.75], "step": 3}, {"value": [0.75], "step": 4}, {"value": [0.75], "step": 5}, {"value": [0.78125], "step": 6}, {"value": [0.78125], "step": 7}, {"value": [0.75], "step": 8}, {"value": [0.78125], "step": 9}]}}}, "score": 0.78125, "best_step": 6, "status": "COMPLETED"}